{
  "date": "2026-06-26",
  "triggers": [
    {
      "ticker": "NOVT",
      "timeframe": "30-MIN",
      "direction": "bearish",
      "conviction": "MED",
      "trigger_type": "PIVOT",
      "theme": "Unclassified",
      "industry": "",
      "industry_rank": 99,
      "theme_rank": 99,
      "weekly_stage": 2,
      "daily_stage": null,
      "trend_template": 8,
      "weekly_bbuw": 41.1,
      "daily_bbuw": 64.1,
      "ep_tier": "NONE",
      "rs_rating": 26,
      "streak_len": 3,
      "pivot_open": 159.73500061035156,
      "pivot_high": 160.58999633789062,
      "pivot_low": 157.83999633789062,
      "pivot_close": 158.8000030517578,
      "pivot_time": "2026-06-26 14:00:00",
      "trigger_open": 154.5883026123047,
      "trigger_high": 154.5883026123047,
      "trigger_low": 153.68499755859375,
      "trigger_close": 153.68499755859375,
      "trigger_time": "2026-06-26 16:00:00",
      "stop_level": 160.59,
      "atr_14d": 7.616,
      "r_ratio": 0.91,
      "rvol_trigger": 0.11,
      "dist_session_high_%": -10.57,
      "dist_ema8w_%": 1.62,
      "trigger_score": 5,
      "or_high": null,
      "or_low": null,
      "or_range": null,
      "breakout_pct": null,
      "entry_note": "ITM/ATM weekly puts",
      "is_cross_day": true,
      "streak_start_date": "2026-06-25",
      "pivot_offset": 5,
      "scan_time": "2026-06-26T16:10:15.776040"
    },
    {
      "ticker": "XIFR",
      "timeframe": "30-MIN",
      "direction": "bearish",
      "conviction": "MED",
      "trigger_type": "PIVOT",
      "theme": "Clean Energy / Power",
      "industry": "Other Alt Energy",
      "industry_rank": 5,
      "theme_rank": 4,
      "weekly_stage": 2,
      "daily_stage": null,
      "trend_template": 8,
      "weekly_bbuw": 45.5,
      "daily_bbuw": 45.4,
      "ep_tier": "NONE",
      "rs_rating": 4,
      "streak_len": 3,
      "pivot_open": 12.039999961853027,
      "pivot_high": 12.039999961853027,
      "pivot_low": 11.964500427246094,
      "pivot_close": 12.039999961853027,
      "pivot_time": "2026-06-26 15:00:00",
      "trigger_open": 11.925000190734863,
      "trigger_high": 11.925000190734863,
      "trigger_low": 11.880000114440918,
      "trigger_close": 11.880000114440918,
      "trigger_time": "2026-06-26 16:00:00",
      "stop_level": 12.04,
      "atr_14d": 0.3698,
      "r_ratio": 0.43,
      "rvol_trigger": 0.05,
      "dist_session_high_%": -10.34,
      "dist_ema8w_%": 3.15,
      "trigger_score": 5,
      "or_high": null,
      "or_low": null,
      "or_range": null,
      "breakout_pct": null,
      "entry_note": "ITM/ATM weekly puts",
      "is_cross_day": false,
      "streak_start_date": "2026-06-26",
      "pivot_offset": 3,
      "scan_time": "2026-06-26T16:10:15.788780"
    },
    {
      "ticker": "WSC",
      "timeframe": "30-MIN",
      "direction": "bearish",
      "conviction": "MED",
      "trigger_type": "PIVOT",
      "theme": "Consumer Discretionary",
      "industry": "Real Estate Operations",
      "industry_rank": 3,
      "theme_rank": 6,
      "weekly_stage": 2,
      "daily_stage": null,
      "trend_template": 7,
      "weekly_bbuw": 64.4,
      "daily_bbuw": 40.5,
      "ep_tier": "NONE",
      "rs_rating": 39,
      "streak_len": 4,
      "pivot_open": 29.059999465942383,
      "pivot_high": 29.059999465942383,
      "pivot_low": 28.850000381469727,
      "pivot_close": 28.90999984741211,
      "pivot_time": "2026-06-26 14:30:00",
      "trigger_open": 28.75,
      "trigger_high": 28.799999237060547,
      "trigger_low": 28.649999618530273,
      "trigger_close": 28.649999618530273,
      "trigger_time": "2026-06-26 16:00:00",
      "stop_level": 29.06,
      "atr_14d": 1.1596,
      "r_ratio": 0.35,
      "rvol_trigger": 0.2,
      "dist_session_high_%": -3.76,
      "dist_ema8w_%": 10.56,
      "trigger_score": 5,
      "or_high": null,
      "or_low": null,
      "or_range": null,
      "breakout_pct": null,
      "entry_note": "ITM/ATM weekly puts",
      "is_cross_day": true,
      "streak_start_date": "2026-06-25",
      "pivot_offset": 4,
      "scan_time": "2026-06-26T16:10:15.795447"
    },
    {
      "ticker": "HTLD",
      "timeframe": "30-MIN",
      "direction": "bearish",
      "conviction": "MED",
      "trigger_type": "PIVOT",
      "theme": "Industrials",
      "industry": "Transportation - Truck",
      "industry_rank": 2,
      "theme_rank": 6,
      "weekly_stage": 2,
      "daily_stage": null,
      "trend_template": 8,
      "weekly_bbuw": 47.0,
      "daily_bbuw": 67.1,
      "ep_tier": "NONE",
      "rs_rating": 48,
      "streak_len": 4,
      "pivot_open": 15.545000076293945,
      "pivot_high": 15.545000076293945,
      "pivot_low": 15.289999961853027,
      "pivot_close": 15.300000190734863,
      "pivot_time": "2026-06-26 15:00:00",
      "trigger_open": 15.260000228881836,
      "trigger_high": 15.279999732971191,
      "trigger_low": 15.25,
      "trigger_close": 15.279999732971191,
      "trigger_time": "2026-06-26 16:30:00",
      "stop_level": 15.545,
      "atr_14d": 0.5224,
      "r_ratio": 0.51,
      "rvol_trigger": 0.14,
      "dist_session_high_%": -8.05,
      "dist_ema8w_%": 6.45,
      "trigger_score": 6,
      "or_high": null,
      "or_low": null,
      "or_range": null,
      "breakout_pct": null,
      "entry_note": "ITM/ATM weekly puts",
      "is_cross_day": true,
      "streak_start_date": "2026-06-25",
      "pivot_offset": 4,
      "scan_time": "2026-06-26T16:31:50.961640"
    },
    {
      "ticker": "ANAB",
      "timeframe": "30-MIN",
      "direction": "bullish",
      "conviction": "MED",
      "trigger_type": "PIVOT",
      "theme": "Unclassified",
      "industry": "",
      "industry_rank": 99,
      "theme_rank": 99,
      "weekly_stage": 2,
      "daily_stage": null,
      "trend_template": 8,
      "weekly_bbuw": 61.5,
      "daily_bbuw": 50.5,
      "ep_tier": "NONE",
      "rs_rating": 78,
      "streak_len": 3,
      "pivot_open": 60.60499954223633,
      "pivot_high": 61.0,
      "pivot_low": 60.47999954223633,
      "pivot_close": 60.88999938964844,
      "pivot_time": "2026-06-26 16:00:00",
      "trigger_open": 61.0,
      "trigger_high": 61.099998474121094,
      "trigger_low": 61.0,
      "trigger_close": 61.01499938964844,
      "trigger_time": "2026-06-26 16:30:00",
      "stop_level": 60.48,
      "atr_14d": 3.0154,
      "r_ratio": 0.18,
      "rvol_trigger": 0.1,
      "dist_session_high_%": -2.09,
      "dist_ema8w_%": 9.15,
      "trigger_score": 4,
      "or_high": null,
      "or_low": null,
      "or_range": null,
      "breakout_pct": null,
      "entry_note": "ITM/ATM weekly calls",
      "is_cross_day": false,
      "streak_start_date": "2026-06-26",
      "pivot_offset": 2,
      "scan_time": "2026-06-26T16:31:50.979427"
    },
    {
      "ticker": "WERN",
      "timeframe": "30-MIN",
      "direction": "bearish",
      "conviction": "MED",
      "trigger_type": "PIVOT",
      "theme": "Industrials",
      "industry": "Transportation - Truck",
      "industry_rank": 2,
      "theme_rank": 6,
      "weekly_stage": 2,
      "daily_stage": null,
      "trend_template": 8,
      "weekly_bbuw": 51.5,
      "daily_bbuw": 62.2,
      "ep_tier": "NONE",
      "rs_rating": 38,
      "streak_len": 5,
      "pivot_open": 42.70000076293945,
      "pivot_high": 42.72999954223633,
      "pivot_low": 42.400001525878906,
      "pivot_close": 42.58000183105469,
      "pivot_time": "2026-06-26 15:00:00",
      "trigger_open": 42.345001220703125,
      "trigger_high": 42.345001220703125,
      "trigger_low": 42.345001220703125,
      "trigger_close": 42.345001220703125,
      "trigger_time": "2026-06-26 17:00:00",
      "stop_level": 42.73,
      "atr_14d": 1.4166,
      "r_ratio": 0.27,
      "rvol_trigger": 0.0,
      "dist_session_high_%": -6.46,
      "dist_ema8w_%": 6.32,
      "trigger_score": 7,
      "or_high": null,
      "or_low": null,
      "or_range": null,
      "breakout_pct": null,
      "entry_note": "ITM/ATM weekly puts",
      "is_cross_day": true,
      "streak_start_date": "2026-06-25",
      "pivot_offset": 5,
      "scan_time": "2026-06-26T17:01:11.687129"
    },
    {
      "ticker": "XIFR",
      "timeframe": "30-MIN",
      "direction": "bullish",
      "conviction": "MED",
      "trigger_type": "PIVOT",
      "theme": "Clean Energy / Power",
      "industry": "Other Alt Energy",
      "industry_rank": 5,
      "theme_rank": 4,
      "weekly_stage": 2,
      "daily_stage": null,
      "trend_template": 8,
      "weekly_bbuw": 45.5,
      "daily_bbuw": 45.4,
      "ep_tier": "NONE",
      "rs_rating": 4,
      "streak_len": 3,
      "pivot_open": 11.859999656677246,
      "pivot_high": 11.920000076293945,
      "pivot_low": 11.859999656677246,
      "pivot_close": 11.920000076293945,
      "pivot_time": "2026-06-26 16:30:00",
      "trigger_open": 11.925000190734863,
      "trigger_high": 11.9399995803833,
      "trigger_low": 11.925000190734863,
      "trigger_close": 11.9399995803833,
      "trigger_time": "2026-06-26 17:00:00",
      "stop_level": 11.86,
      "atr_14d": 0.3698,
      "r_ratio": 0.22,
      "rvol_trigger": 0.13,
      "dist_session_high_%": -9.89,
      "dist_ema8w_%": 3.67,
      "trigger_score": 4,
      "or_high": null,
      "or_low": null,
      "or_range": null,
      "breakout_pct": null,
      "entry_note": "ITM/ATM weekly calls",
      "is_cross_day": false,
      "streak_start_date": "2026-06-26",
      "pivot_offset": 2,
      "scan_time": "2026-06-26T17:17:59.251433"
    },
    {
      "ticker": "RAMP",
      "timeframe": "30-MIN",
      "direction": "bullish",
      "conviction": "MED",
      "trigger_type": "PIVOT",
      "theme": "Unclassified",
      "industry": "",
      "industry_rank": 99,
      "theme_rank": 99,
      "weekly_stage": 2,
      "daily_stage": null,
      "trend_template": 8,
      "weekly_bbuw": 67.5,
      "daily_bbuw": 60.4,
      "ep_tier": "NONE",
      "rs_rating": 27,
      "streak_len": 4,
      "pivot_open": 37.56999969482422,
      "pivot_high": 37.59000015258789,
      "pivot_low": 37.560001373291016,
      "pivot_close": 37.59000015258789,
      "pivot_time": "2026-06-26 17:30:00",
      "trigger_open": 37.59000015258789,
      "trigger_high": 37.595001220703125,
      "trigger_low": 37.584999084472656,
      "trigger_close": 37.595001220703125,
      "trigger_time": "2026-06-26 18:00:00",
      "stop_level": 37.56,
      "atr_14d": 0.244,
      "r_ratio": 0.14,
      "rvol_trigger": 0.1,
      "dist_session_high_%": -0.86,
      "dist_ema8w_%": 7.03,
      "trigger_score": 6,
      "or_high": null,
      "or_low": null,
      "or_range": null,
      "breakout_pct": null,
      "entry_note": "ITM/ATM weekly calls",
      "is_cross_day": false,
      "streak_start_date": "2026-06-26",
      "pivot_offset": 2,
      "scan_time": "2026-06-26T18:09:20.000197"
    },
    {
      "ticker": "TRVI",
      "timeframe": "30-MIN",
      "direction": "bullish",
      "conviction": "MED",
      "trigger_type": "PIVOT",
      "theme": "Unclassified",
      "industry": "",
      "industry_rank": 99,
      "theme_rank": 99,
      "weekly_stage": 2,
      "daily_stage": null,
      "trend_template": 8,
      "weekly_bbuw": 49.3,
      "daily_bbuw": 40.2,
      "ep_tier": "STANDARD",
      "rs_rating": 55,
      "streak_len": 3,
      "pivot_open": 17.729999542236328,
      "pivot_high": 17.844999313354492,
      "pivot_low": 17.704999923706055,
      "pivot_close": 17.795000076293945,
      "pivot_time": "2026-06-26 17:30:00",
      "trigger_open": 17.795000076293945,
      "trigger_high": 17.8799991607666,
      "trigger_low": 17.790000915527344,
      "trigger_close": 17.8799991607666,
      "trigger_time": "2026-06-26 18:00:00",
      "stop_level": 17.705,
      "atr_14d": 0.8695,
      "r_ratio": 0.2,
      "rvol_trigger": 0.12,
      "dist_session_high_%": -1.54,
      "dist_ema8w_%": 22.62,
      "trigger_score": 4,
      "or_high": null,
      "or_low": null,
      "or_range": null,
      "breakout_pct": null,
      "entry_note": "ITM/ATM weekly calls",
      "is_cross_day": false,
      "streak_start_date": "2026-06-26",
      "pivot_offset": 2,
      "scan_time": "2026-06-26T18:09:20.016993"
    }
  ]
}